text_processing_util_mds24/__init__.py
text_processing_util_mds24/text_processing_util_mds24.py
text_processing_util_mds24-2.2.4.dist-info/LICENSE
text_processing_util_mds24-2.2.4.dist-info/METADATA
text_processing_util_mds24-2.2.4.dist-info/WHEEL
text_processing_util_mds24-2.2.4.dist-info/RECORD
