Metadata-Version: 2.1
Name: text_processing_util_mds24
Version: 2.2.4
Summary: Utility functions for text processing.
License: MIT
Author: Jerry Yu, Nasim Ghazanfari Nasrabadi, Mohammad Norouzi, Allan Lee
Requires-Python: >=3.9
Classifier: License :: OSI Approved :: MIT License
Classifier: Programming Language :: Python :: 3
Classifier: Programming Language :: Python :: 3.9
Classifier: Programming Language :: Python :: 3.10
Classifier: Programming Language :: Python :: 3.11
Classifier: Programming Language :: Python :: 3.12
Requires-Dist: numpy (>=1.26.3)
